endpoints/__init__.py
endpoints/posts.py
endpoints/wiki_pages.py
applebooru-1.0.0b3.dist-info/METADATA
applebooru-1.0.0b3.dist-info/WHEEL
applebooru-1.0.0b3.dist-info/top_level.txt
applebooru-1.0.0b3.dist-info/RECORD
