Metadata-Version: 2.2
Name: applebooru
Version: 1.0.0b3
Summary: A wrapper for Danbooru API
Home-page: https://github.com/AppleHarem/AppleBooru
Author: ChenMoe
Classifier: Programming Language :: Python :: 3
Classifier: License :: OSI Approved :: MIT License
Classifier: Operating System :: OS Independent
Requires-Python: >=3.6
Requires-Dist: requests>=2.25.1
Dynamic: author
Dynamic: classifier
Dynamic: description
Dynamic: description-content-type
Dynamic: home-page
Dynamic: requires-dist
Dynamic: requires-python
Dynamic: summary
